[{"hs_code":"0104.10.10","six_digit":"0104.10","final_desc":"- - Bebek :Unggas hidup, yaitu ayam dari spesies\u00a0Gallus domesticus, bebek, angsa, kalkun dan ayam guinea.;- - Ducks :Live poultry, that is to say, fowls of the species\u00a0Gallus domesticus, ducks, geese, turkeys and guinea fowls.;- - Pure-bred breeding animals- - Bibit"},{"hs_code":"0104.10.90","six_digit":"0104.10","final_desc":"- - Angsa :Unggas hidup, yaitu ayam dari spesies\u00a0Gallus domesticus, bebek, angsa, kalkun dan ayam guinea.;- - Geese :Live poultry, that is to say, fowls of the species\u00a0Gallus domesticus, ducks, geese, turkeys and guinea fowls.;- - Other- - Lain-lain"}]