[{"hs_code":"0713.60.10","six_digit":"0713.60","final_desc":"- Lesitin dan fosfoaminolipid lainnya :Garam dan hidroksida amonium kuarterner; lesitin dan fosfoaminolipid lainnya, mempunyai rumus kimia tertentu maupun tidak.;- Lecithins and other phosphoaminolipids :Quaternary ammonium salts and hydroxides; lecithins and other phosphoaminolipids, whether or not chemically defined.;- - Suitable for sowing- - Cocok untuk disemai"},{"hs_code":"0713.60.90","six_digit":"0713.60","final_desc":"- - Fluoroasetamida (ISO), monokrotofos (ISO) dan fosfamidon (ISO) :Senyawa berfungsi karboksiamida; senyawa berfungsi amida dari asam karbonat.;- - Fluoroacetamide (ISO), monocrotophos (ISO) and phosphamidon (ISO) :Carboxyamide-function compounds; amide-function compounds of carbonic acid.;- - Other- - Lain-lain"}]