[{"hs_code":"3204.12.10","six_digit":"3204.12","final_desc":"- Mesin pemintal benang tekstil :Mesin untuk pengolahan serat tekstil; mesin pemintal, pengganda atau pemilin dan mesin lainnya untuk memproduksi benang tekstil; mesin pengikal atau penggulung tekstil (termasuk penggulung benang pakan) dan mesin untuk menyiapkan benang tekstil untuk digunakan pada mesin dari pos 84.46 atau 84.47.;- Textile spinning machines :Machines for preparing textile fibres; spinning, doubling or twisting machines and other machinery for producing textile yarns; textile reeling or winding (including weft-winding) machines and machines for preparing textile yarns for use on the machines of heading 84.46 or 84.47.;- - - Acid dyes- - - Bahan celup asam"},{"hs_code":"3204.12.90","six_digit":"3204.12","final_desc":"- Mesin pengganda atau pemintal benang tekstil :Mesin untuk pengolahan serat tekstil; mesin pemintal, pengganda atau pemilin dan mesin lainnya untuk memproduksi benang tekstil; mesin pengikal atau penggulung tekstil (termasuk penggulung benang pakan) dan mesin untuk menyiapkan benang tekstil untuk digunakan pada mesin dari pos 84.46 atau 84.47.;- Textile doubling or twisting machines :Machines for preparing textile fibres; spinning, doubling or twisting machines and other machinery for producing textile yarns; textile reeling or winding (including weft-winding) machines and machines for preparing textile yarns for use on the machines of heading 84.46 or 84.47.;- - - Other- - - Lain-lain"}]