[{"hs_code":"3405.40.20","six_digit":"3405.40","final_desc":"- Peralatan lainnya :Keran, klep, katup dan peralatan semacam itu untuk pipa, dinding ketel uap, tangki, tong atau sejenisnya, termasuk katup pengurang tekanan dan katup yang dikendalikan secara termostatik.;- Other appliances :Taps, cocks, valves and similar appliances for pipes, boiler shells, tanks, vats or the like, including pressure-reducing valves and thermostatically controlled valves.;- - In packaging of a net weight not exceeding 1 kg- - Dalam kemasan dengan berat bersih tidak melebihi 1 kg"},{"hs_code":"3405.40.90","six_digit":"3405.40","final_desc":"- Bagian :Keran, klep, katup dan peralatan semacam itu untuk pipa, dinding ketel uap, tangki, tong atau sejenisnya, termasuk katup pengurang tekanan dan katup yang dikendalikan secara termostatik.;- Parts :Taps, cocks, valves and similar appliances for pipes, boiler shells, tanks, vats or the like, including pressure-reducing valves and thermostatically controlled valves.;- - Other- - Lain-lain"}]