[{"hs_code":"8703.90.11","six_digit":"8703.90","final_desc":null},{"hs_code":"8703.90.12","six_digit":"8703.90","final_desc":null},{"hs_code":"8703.90.13","six_digit":"8703.90","final_desc":null},{"hs_code":"8703.90.14","six_digit":"8703.90","final_desc":null},{"hs_code":"8703.90.15","six_digit":"8703.90","final_desc":null},{"hs_code":"8703.90.16","six_digit":"8703.90","final_desc":null},{"hs_code":"8703.90.17","six_digit":"8703.90","final_desc":null},{"hs_code":"8703.90.18","six_digit":"8703.90","final_desc":null},{"hs_code":"8703.90.19","six_digit":"8703.90","final_desc":null},{"hs_code":"8703.90.91","six_digit":"8703.90","final_desc":null},{"hs_code":"8703.90.92","six_digit":"8703.90","final_desc":null},{"hs_code":"8703.90.93","six_digit":"8703.90","final_desc":null},{"hs_code":"8703.90.94","six_digit":"8703.90","final_desc":null},{"hs_code":"8703.90.95","six_digit":"8703.90","final_desc":null},{"hs_code":"8703.90.96","six_digit":"8703.90","final_desc":null},{"hs_code":"8703.90.97","six_digit":"8703.90","final_desc":null},{"hs_code":"8703.90.98","six_digit":"8703.90","final_desc":null},{"hs_code":"8703.90.99","six_digit":"8703.90","final_desc":null}]